{"nodes": [{"id": "api_routers_health_py", "label": "health.py", "file_type": "code", "source_file": "api/routers/health.py", "source_location": "L1"}, {"id": "health_health", "label": "health()", "file_type": "code", "source_file": "api/routers/health.py", "source_location": "L11"}, {"id": "health_rationale_1", "label": "Health check endpoint.", "file_type": "rationale", "source_file": "api/routers/health.py", "source_location": "L1"}, {"id": "health_rationale_12", "label": "Pipeline status, last run timestamp, and database stats.", "file_type": "rationale", "source_file": "api/routers/health.py", "source_location": "L12"}], "edges": [{"source": "api_routers_health_py", "target": "datetime", "relation": "imports_from", "confidence": "EXTRACTED", "source_file": "api/routers/health.py", "source_location": "L3", "weight": 1.0}, {"source": "api_routers_health_py", "target": "fastapi", "relation": "imports_from", "confidence": "EXTRACTED", "source_file": "api/routers/health.py", "source_location": "L4", "weight": 1.0}, {"source": "api_routers_health_py", "target": "api_deps", "relation": "imports_from", "confidence": "EXTRACTED", "source_file": "api/routers/health.py", "source_location": "L5", "weight": 1.0}, {"source": "api_routers_health_py", "target": "health_health", "relation": "contains", "confidence": "EXTRACTED", "source_file": "api/routers/health.py", "source_location": "L11", "weight": 1.0}, {"source": "health_rationale_1", "target": "api_routers_health_py", "relation": "rationale_for", "confidence": "EXTRACTED", "source_file": "api/routers/health.py", "source_location": "L1", "weight": 1.0}, {"source": "health_rationale_12", "target": "health_health", "relation": "rationale_for", "confidence": "EXTRACTED", "source_file": "api/routers/health.py", "source_location": "L12", "weight": 1.0}]}