{"nodes": [{"id": "scripts_train_v1_3_ensemble_py", "label": "train_v1_3_ensemble.py", "file_type": "code", "source_file": "scripts/train_v1_3_ensemble.py", "source_location": "L1"}, {"id": "train_v1_3_ensemble_main", "label": "main()", "file_type": "code", "source_file": "scripts/train_v1_3_ensemble.py", "source_location": "L63"}, {"id": "train_v1_3_ensemble_rationale_1", "label": "Train a bootstrap-aggregated ensemble of the v1_3 regressor.  The existing v1_3", "file_type": "rationale", "source_file": "scripts/train_v1_3_ensemble.py", "source_location": "L1"}], "edges": [{"source": "scripts_train_v1_3_ensemble_py", "target": "datetime", "relation": "imports", "confidence": "EXTRACTED", "source_file": "scripts/train_v1_3_ensemble.py", "source_location": "L25", "weight": 1.0}, {"source": "scripts_train_v1_3_ensemble_py", "target": "json", "relation": "imports", "confidence": "EXTRACTED", "source_file": "scripts/train_v1_3_ensemble.py", "source_location": "L26", "weight": 1.0}, {"source": "scripts_train_v1_3_ensemble_py", "target": "logging", "relation": "imports", "confidence": "EXTRACTED", "source_file": "scripts/train_v1_3_ensemble.py", "source_location": "L27", "weight": 1.0}, {"source": "scripts_train_v1_3_ensemble_py", "target": "sys", "relation": "imports", "confidence": "EXTRACTED", "source_file": "scripts/train_v1_3_ensemble.py", "source_location": "L28", "weight": 1.0}, {"source": "scripts_train_v1_3_ensemble_py", "target": "pathlib", "relation": "imports_from", "confidence": "EXTRACTED", "source_file": "scripts/train_v1_3_ensemble.py", "source_location": "L29", "weight": 1.0}, {"source": "scripts_train_v1_3_ensemble_py", "target": "lightgbm", "relation": "imports", "confidence": "EXTRACTED", "source_file": "scripts/train_v1_3_ensemble.py", "source_location": "L33", "weight": 1.0}, {"source": "scripts_train_v1_3_ensemble_py", "target": "numpy", "relation": "imports", "confidence": "EXTRACTED", "source_file": "scripts/train_v1_3_ensemble.py", "source_location": "L34", "weight": 1.0}, {"source": "scripts_train_v1_3_ensemble_py", "target": "db_connection", "relation": "imports_from", "confidence": "EXTRACTED", "source_file": "scripts/train_v1_3_ensemble.py", "source_location": "L36", "weight": 1.0}, {"source": "scripts_train_v1_3_ensemble_py", "target": "pipeline_model_features", "relation": "imports_from", "confidence": "EXTRACTED", "source_file": "scripts/train_v1_3_ensemble.py", "source_location": "L37", "weight": 1.0}, {"source": "scripts_train_v1_3_ensemble_py", "target": "train_v1_3_ensemble_main", "relation": "contains", "confidence": "EXTRACTED", "source_file": "scripts/train_v1_3_ensemble.py", "source_location": "L63", "weight": 1.0}, {"source": "train_v1_3_ensemble_rationale_1", "target": "scripts_train_v1_3_ensemble_py", "relation": "rationale_for", "confidence": "EXTRACTED", "source_file": "scripts/train_v1_3_ensemble.py", "source_location": "L1", "weight": 1.0}]}